explaineval/__init__.py
explaineval/main.py
explaineval/core/__init__.py
explaineval/core/base.py
explaineval/core/classification.py
explaineval/core/nlp.py
explaineval/core/regression.py
explaineval/core/timeseries.py
explaineval/explainers/__init__.py
explaineval/explainers/base_explainer.py
explaineval/explainers/lime_explainer.py
explaineval/explainers/shap_explainer.py
explaineval/explainers/transformer_explainer.py
explaineval/utils/__init__.py
explaineval/utils/logger.py
explaineval/utils/metrics.py
explaineval/visualizer/__init__.py
explaineval/visualizer/dashboard.py
explaineval/visualizer/plots.py
explaineval/visualizer/report_template.html
explaineval-0.2.5.dist-info/METADATA
explaineval-0.2.5.dist-info/WHEEL
explaineval-0.2.5.dist-info/top_level.txt
explaineval-0.2.5.dist-info/RECORD
