Metadata-Version: 2.4
Name: explaineval
Version: 0.2.5
Summary: Unified evaluation and explainability framework for ML models
Home-page: https://github.com/shaheerzk01/ExplainEval_python_package
Author: Shaheer Zaman Khan
Author-email: shaheerzk01@gmail.com
License: MIT
Classifier: Programming Language :: Python :: 3
Classifier: License :: OSI Approved :: MIT License
Classifier: Intended Audience :: Developers
Classifier: Topic :: Scientific/Engineering :: Artificial Intelligence
Requires-Python: >=3.7
Requires-Dist: scikit-learn
Requires-Dist: matplotlib
Requires-Dist: seaborn
Requires-Dist: shap
Requires-Dist: lime
Requires-Dist: jinja2
Requires-Dist: pandas
